pyproject.toml
PKG-INFO
setup.cfg
setup.py
ringo.egg-info/top_level.txt
ringo.egg-info/SOURCES.txt
ringo.egg-info/dependency_links.txt
ringo.egg-info/PKG-INFO
ringo.egg-info/requires.txt
ringo/ringo_base.cpython-39-x86_64-linux-gnu.so
ringo/graph_utils.py
ringo/ringo_base.cpython-314-x86_64-linux-gnu.so
ringo/ringo_base.cpython-313-x86_64-linux-gnu.so
ringo/ringo_base.cpython-312-x86_64-linux-gnu.so
ringo/__init__.py
ringo/ringo_base.cpython-311-x86_64-linux-gnu.so
ringo/ringo_base.pyi
ringo/ringo_base.cpython-310-x86_64-linux-gnu.so
ringo/cpppart/cpppart.py
ringo/test/utils.py
ringo/test/tests.py
ringo/test/__init__.py
ringo/test/pdb7UPJ.sdf
ringo/test/pdb1GHG.sdf
ringo/pyxyz/molgraph.py
ringo/pyxyz/base_load.py
ringo/pyxyz/__init__.py
ringo/pyxyz/cpppart/cpppart.py
ringo/pyxyz/test/utils.py
ringo/pyxyz/test/aminoacid_ensemble.xyz
ringo/pyxyz/test/aminoacid_ensemble_current.xyz
ringo/pyxyz/test/crest_conformersA.xyz
ringo/pyxyz/test/aminoacid_ensemble_ref.xyz
ringo/pyxyz/test/geom_analysis.xyz
ringo/pyxyz/test/tests.py
ringo/pyxyz/test/__init__.py
ringo/pyxyz/test/aminoacid_single.xyz
ringo/pyxyz/test/hydrogen_atom.xyz
ringo/pyxyz/test/crest_conformersB.xyz
ringo/pyxyz/pyutils/utils.py
ringo/pyxyz/pyutils/moltopology.py
ringo/pyxyz/pyutils/__init__.py
ringo/pyutils/utils.py
ringo/pyutils/moltopology.py
ringo/pyutils/__init__.py
ringo/pyutils/cyclicpart.py
mcr/mcr.py
mcr/__main__.py
mcr/custom_sampling.py
mcr/timeparse.py
mcr/__init__.py