Metadata-Version: 2.1
Name: ringo_ik
Version: 1.0.14
Author: Nikolai Krivoshchapov
Platform: Linux
Requires-Python: >= 3.9.0
Summary: Ringo –⁠ The Python Library for Kinematics-Driven Conformer Generation
Project-URL: Gitlab home page, https://gitlab.com/knvvv/ringo
Project-URL: Docs, https://knvvv.gitlab.io/ringo
